speedmon/Controller.py
speedmon/SpeedMonitor.py
speedmon/__init__.py
speedmon/__main__.py
speedmon-1.0.0.dist-info/LICENSE.md
speedmon-1.0.0.dist-info/METADATA
speedmon-1.0.0.dist-info/WHEEL
speedmon-1.0.0.dist-info/entry_points.txt
speedmon-1.0.0.dist-info/top_level.txt
speedmon-1.0.0.dist-info/RECORD
