Metadata-Version: 2.1
Name: speedmon
Version: 1.0.0
Summary: Performance Monitoring Capabilities
Home-page: https://github.com/5f0ne/speedmon
Author: 5f0
License: MIT
Classifier: Operating System :: OS Independent 
Classifier: Programming Language :: Python :: 3 
Classifier: License :: OSI Approved :: MIT License 
License-File: LICENSE.md
